sending/__init__.py
sending/backends/jupyter.py
sending/backends/memory.py
sending/backends/redis.py
sending/backends/websocket.py
sending/base.py
sending/logging.py
sending/util.py
sending-0.3.0.dist-info/METADATA
sending-0.3.0.dist-info/WHEEL
sending-0.3.0.dist-info/RECORD
